{
  "request": {
    "exactUrl": [
      "/api/pass/v1/share/2AM2tz_3SLukj5ILxkqalK7KrFsW1rJ4R5ccGBpqAIIdS1kAxa9g4SbY39Alg2q11V7Bay85K_GRP1hD0M4VyA==/event"
    ],
    "method": "get"
  },
  "response": {
    "body": {
      "Code": 1000,
      "EventID": "dKyUiGFmMaswF-g0fgjsC62tcG53rXPhpekt9HCt7mPkD6HZ5hgrP_Z1wA06w2inlMXWHKxtJfxKDwMv2dDPYQ=="
    },
    "headers": {
      "server": "nginx",
      "date": "Fri, 28 Feb 2025 13:38:19 GMT",
      "content-type": "application/json",
      "transfer-encoding": "chunked",
      "connection": "close",
      "x-pm-code": "1000",
      "cache-control": "max-age=0, must-revalidate, no-cache, no-store, private",
      "expires": "Fri, 04 May 1984 22:15:00 GMT",
      "x-pm-route-pattern": "GET /pass/v1/share/{enc_shareID}/event",
      "x-pm-user-id": "968",
      "x-pm-uid": "uiq4rtapgafsupgmnagm2dmfoya7xv4j",
      "access": "application/vnd.protonmail.api+json;apiversion=1",
      "x-pm-time-total": "490",
      "x-pm-time-user": "462",
      "x-pm-time-system": "0",
      "x-pm-memory": "8",
      "x-pm-allocated-memory": "10",
      "x-pm-urgency": "1",
      "x-pm-apiversion": "develop (407a425c)",
      "x-b3-traceid": "d818b6be10536b3f6d5c5da91f493ba9",
      "x-b3-spanid": "cf619f4f6db88b5a",
      "x-b3-parentspanid": "",
      "vary": "Accept-Encoding",
      "content-encoding": "gzip",
      "x-pm-nonce": "Z8G8So4vpkX7SM3lIZ7ZMgAAAM4",
      "set-cookie": [
        "Session-Id=Z8G8So4vpkX7SM3lIZ7ZMgAAAM4; Domain=payne-gaposchkin.proton.black; Path=/; HttpOnly; Secure; Max-Age=7776000",
        "Version=; Domain=payne-gaposchkin.proton.black; Path=/; Secure; Expires=Thu, 01 Jan 1970 00:00:00 GMT"
      ],
      "strict-transport-security": "max-age=15724800; includeSubDomains, max-age=31536000; includeSubDomains; preload, max-age=63072000",
      "content-security-policy": "default-src 'self'; script-src 'self' 'unsafe-eval' 'nonce-Z8G8So4vpkX7SM3lIZ7ZMgAAAM4' 'strict-dynamic' https:; style-src 'self' 'unsafe-inline'; img-src http: https: data: blob: cid:; font-src 'self' https://*.payne-gaposchkin.proton.black; frame-src https:; connect-src https: wss:; media-src https:; frame-ancestors https://*.mock.proton.black/ https://*.payne-gaposchkin.proton.black;",
      "expect-ct": "max-age=2592000, enforce",
      "x-content-type-options": "nosniff",
      "x-xss-protection": "1; mode=block",
      "referrer-policy": "strict-origin-when-cross-origin",
      "x-permitted-cross-domain-policies": "none"
    },
    "statusCode": 200
  },
  "enabled": true,
  "name": "Mock_get__api_pass_v1_share_2AM2tz_3SLukj5ILxkqalK7KrFsW1rJ4R5ccGBpqAIIdS1kAxa9g4SbY39Alg2q11V7Bay85K_GRP1hD0M4VyA___event"
}